mcpk/__init__.py
mcpk/_base.py
mcpk/_enforce.py
mcpk/_registry.py
mcpk/_runtime.py
mcpk/errors.py
mcpk/events.py
mcpk/hooks.py
mcpk/kernel.py
mcpk/py.typed
mcpk/types.py
mcpk/validation.py
mcpk-0.1.0.dist-info/METADATA
mcpk-0.1.0.dist-info/WHEEL
mcpk-0.1.0.dist-info/licenses/LICENSE
mcpk-0.1.0.dist-info/RECORD
