Metadata-Version: 2.4
Name: mcpk
Version: 0.1.0
Summary: A transport-agnostic kernel for MCP servers
Project-URL: Homepage, https://github.com/ahopkins/mcpk
Project-URL: Repository, https://github.com/ahopkins/mcpk
Project-URL: Issues, https://github.com/ahopkins/mcpk/issues
Author-email: Adam Hopkins <adam@amhopkins.com>
License-Expression: MIT
License-File: LICENSE
Keywords: ai,llm,mcp,model-context-protocol,server
Classifier: Development Status :: 4 - Beta
Classifier: Intended Audience :: Developers
Classifier: License :: OSI Approved :: MIT License
Classifier: Operating System :: OS Independent
Classifier: Programming Language :: Python :: 3
Classifier: Programming Language :: Python :: 3.12
Classifier: Programming Language :: Python :: 3.13
Classifier: Typing :: Typed
Requires-Python: >=3.12
Provides-Extra: validation
Requires-Dist: jsonschema>=4.0; extra == 'validation'
